ul/__init__.py
ul-0.0.6.dist-info/licenses/LICENSE
ul-0.0.6.dist-info/METADATA
ul-0.0.6.dist-info/WHEEL
ul-0.0.6.dist-info/top_level.txt
ul-0.0.6.dist-info/RECORD
