Metadata-Version: 2.4
Name: ul
Version: 0.0.6
Summary: Generate Unified Lattices that show you how a set of functions are related to each other
Home-page: https://github.com/cavart28/ul
Author: C Avart
License: apache-2.0
Platform: any
License-File: LICENSE
Requires-Dist: openai
Requires-Dist: networkx
Dynamic: license-file
